bns_utils/TransferFunction.py
bns_utils/__init__.py
bns_utils/data.py
bns_utils/fluidreports.py
bns_utils/general.py
bns_utils/monitor.py
bns_utils-0.0.5.dist-info/LICENSE
bns_utils-0.0.5.dist-info/METADATA
bns_utils-0.0.5.dist-info/WHEEL
bns_utils-0.0.5.dist-info/top_level.txt
bns_utils-0.0.5.dist-info/RECORD
