Metadata-Version: 2.1
Name: bns-utils
Version: 0.0.5
Summary: Some utilities for BNS internal use
Author-email: Example Author <author@example.com>
Project-URL: Homepage, https://github.com/Dave-the-python-developer/BNS_utils
Project-URL: PyPi, https://pypi.org/project/bns-utils/
Classifier: Programming Language :: Python :: 3
Classifier: License :: OSI Approved :: MIT License
Classifier: Operating System :: OS Independent
Requires-Python: >=3.7
License-File: LICENSE
Requires-Dist: matplotlib (<5,>=3.5.0)
Requires-Dist: pandas (<2,>=1.5.0)
Requires-Dist: scipy (<2,>=1.9.0)
